nutrimium/__init__.py
nutrimium-0.0.5.dist-info/LICENSE
nutrimium-0.0.5.dist-info/METADATA
nutrimium-0.0.5.dist-info/WHEEL
nutrimium-0.0.5.dist-info/entry_points.txt
nutrimium-0.0.5.dist-info/top_level.txt
nutrimium-0.0.5.dist-info/RECORD
